tlp_classifier/__init__.py
tlp_classifier/__main__.py
tlp_classifier/algorithms.py
tlp_classifier/api.py
tlp_classifier/classifier.py
tlp_classifier/complexity.py
tlp_classifier/file_help.py
tlp_classifier/generator.py
tlp_classifier/input.py
tlp_classifier/problem.py
tlp_classifier/problem_set.py
tlp_classifier/tools.py
tlp_classifier/two_labels_classifier.py
tlp_classifier/data/problemSet_2_2_C
tlp_classifier/data/problemSet_2_3_C
tlp_classifier-0.1.10.data/data/data/problemSet_2_2_C
tlp_classifier-0.1.10.data/data/data/problemSet_2_3_C
tlp_classifier-0.1.10.dist-info/AUTHORS
tlp_classifier-0.1.10.dist-info/COPYING.txt
tlp_classifier-0.1.10.dist-info/LICENSE
tlp_classifier-0.1.10.dist-info/METADATA
tlp_classifier-0.1.10.dist-info/WHEEL
tlp_classifier-0.1.10.dist-info/top_level.txt
tlp_classifier-0.1.10.dist-info/RECORD
