Metadata-Version: 2.1
Name: tlp-classifier
Version: 0.1.10
Summary: A command-line tool for automatically classifying ternary labelling problems (hence TLP) on bipartite trees.
Home-page: https://github.com/AleksTeresh/tlp-classifier
Author: Tanguy Rocher, Aleksandr Tereshchenko
Author-email: tanguy.rocher@epfl.ch, aleksandr.tereshch@gmail.com
License: MIT
Platform: UNKNOWN
Classifier: License :: OSI Approved :: MIT License
Classifier: Programming Language :: Python :: 3
Classifier: Programming Language :: Python :: 3.8
Requires-Dist: tqdm
Requires-Dist: bitarray
Requires-Dist: numpy
